era/__init__.py
era/era.py
era/era_const.py
era/era_micro.py
era/era_protocol.py
era/era_timer.py
era/era_wifi.py
eralibpy_mp-0.4.1.dist-info/LICENSE
eralibpy_mp-0.4.1.dist-info/METADATA
eralibpy_mp-0.4.1.dist-info/WHEEL
eralibpy_mp-0.4.1.dist-info/top_level.txt
eralibpy_mp-0.4.1.dist-info/RECORD
