Metadata-Version: 2.1
Name: eralibpy-mp
Version: 0.4.1
Summary: ERa Python/Micropython library
Home-page: https://github.com/eoh-jsc/era-lib-py
Author: EoH Ltd
Author-email: info@eoh.io
License: MIT
Classifier: Programming Language :: Python :: 3.7
Classifier: Programming Language :: Python :: 3.8
Classifier: Programming Language :: Python :: 3.9
Classifier: Programming Language :: Python :: 3.10
Classifier: Programming Language :: Python :: 3.11
Classifier: Programming Language :: Python :: 3.12
Classifier: License :: OSI Approved :: MIT License
Classifier: Operating System :: OS Independent
Requires-Python: >=3.7
License-File: LICENSE
